dateweek/__init__.py
dateweek/dateweek.py
dateweek-0.1.1.dist-info/LICENSE
dateweek-0.1.1.dist-info/WHEEL
dateweek-0.1.1.dist-info/METADATA
dateweek-0.1.1.dist-info/RECORD
